nospoon_integrations/__init__.py
nospoon_integrations/client.py
nospoon_integrations/core/__init__.py
nospoon_integrations/core/errors.py
nospoon_integrations/core/types.py
nospoon_integrations/providers/__init__.py
nospoon_integrations/providers/base_provider.py
nospoon_integrations/providers/facebook.py
nospoon_integrations/providers/google.py
nospoon_integrations/providers/hubspot.py
nospoon_integrations/providers/linkedin.py
nospoon_integrations/providers/microsoft.py
nospoon_integrations/storage/__init__.py
nospoon_integrations/storage/base.py
nospoon_integrations/storage/memory.py
nospoon_integrations/storage/supabase.py
nospoon_integrations/utils/__init__.py
nospoon_integrations/utils/state_token.py
nospoon_integrations-0.2.2.dist-info/METADATA
nospoon_integrations-0.2.2.dist-info/WHEEL
nospoon_integrations-0.2.2.dist-info/RECORD
